webviewpy/__init__.py
webviewpy/__init__.pyi
webviewpy/__version__.py
webviewpy/platform/darwin/x64/libwebview.dylib
webviewpy/platform/linux/x64/libwebview.so
webviewpy/platform/win32/x64/webview.dll
webviewpy/platform/win32/x86/webview.dll
webviewpy/tools/__init__.py
webviewpy/tools/__pyinstaller/__init__.py
webviewpy/tools/__pyinstaller/hook-webviewpy.py
webviewpy-1.5.1.dist-info/LICENSE
webviewpy-1.5.1.dist-info/METADATA
webviewpy-1.5.1.dist-info/WHEEL
webviewpy-1.5.1.dist-info/entry_points.txt
webviewpy-1.5.1.dist-info/top_level.txt
webviewpy-1.5.1.dist-info/RECORD
