Metadata-Version: 2.2
Name: webviewpy
Version: 1.5.1
Summary: ctypes binding of webview
Author: HIllya51
License: Copyright (c) 2013, Aldo Cortesi. All rights reserved.
Project-URL: Homepage, https://github.com/HIllya51/webviewpy
Project-URL: Repository, https://github.com/HIllya51/webviewpy
Classifier: License :: OSI Approved :: MIT License
Classifier: Operating System :: OS Independent
Classifier: Programming Language :: Python :: 3
Classifier: Programming Language :: Python :: 3.7
Classifier: Programming Language :: Python :: 3.8
Classifier: Programming Language :: Python :: 3.9
Classifier: Programming Language :: Python :: 3.10
Classifier: Programming Language :: Python :: 3.11
Classifier: Programming Language :: Python :: 3.12
Classifier: Programming Language :: Python :: 3.13
Requires-Python: >=3.7
License-File: LICENSE
